main.py
src/__init__.py
src/agent.py
src/app.py
src/database.py
src/downloader.py
src/interface.py
src/processor.py
src/search.py
markdown_semantic_search-1.4.0.dist-info/METADATA
markdown_semantic_search-1.4.0.dist-info/WHEEL
markdown_semantic_search-1.4.0.dist-info/entry_points.txt
markdown_semantic_search-1.4.0.dist-info/RECORD
