Metadata-Version: 2.4
Name: markdown-semantic-search
Version: 1.4.0
Summary: 🤖 Markdown Semantic Search CLI - Search your markdown docs naturally without embeddings.
Project-URL: Homepage, https://github.com/chotabuziness/markdown-semantic-search
Project-URL: Repository, https://github.com/chotabuziness/markdown-semantic-search
Author: Ezazul Haq
License: MIT
Keywords: cli,duckdb,markdown,no-embeddings,semantic-search,tfidf
Classifier: Environment :: Console
Classifier: Intended Audience :: Developers
Classifier: License :: OSI Approved :: MIT License
Classifier: Operating System :: OS Independent
Classifier: Programming Language :: Python :: 3
Classifier: Topic :: Scientific/Engineering :: Artificial Intelligence
Classifier: Topic :: Text Processing :: Markup :: Markdown
Requires-Python: >=3.12
Requires-Dist: duckdb>=1.4.3
Requires-Dist: langchain-openai>=1.1.7
Requires-Dist: langchain>=1.2.6
Requires-Dist: langgraph>=1.0.6
Requires-Dist: python-dotenv>=1.2.1
Requires-Dist: requests>=2.32.5
